fpt/__init__.py
fpt/__version__.py
fpt/api.py
fpt/main.py
fpt_cli-2023.1.dist-info/LICENSE
fpt_cli-2023.1.dist-info/METADATA
fpt_cli-2023.1.dist-info/WHEEL
fpt_cli-2023.1.dist-info/entry_points.txt
fpt_cli-2023.1.dist-info/top_level.txt
fpt_cli-2023.1.dist-info/RECORD
