Metadata-Version: 2.1
Name: fpt-cli
Version: 2023.1
Summary: Estadísticas de la primera división del fútbol argentino por línea de comandos.
Home-page: https://github.com/el-ega/fpt-cli
Author: Matias Bordese
Author-email: mbordese@gmail.com
License: MIT
Keywords: fútbol,argentina,resultados,estadísticas
Classifier: Development Status :: 4 - Beta
Classifier: License :: OSI Approved :: MIT License
Classifier: Programming Language :: Python
Classifier: Programming Language :: Python :: 2.7
Classifier: Programming Language :: Python :: 3
Classifier: Topic :: Utilities
License-File: LICENSE
Requires-Dist: click (>=5.0)
Requires-Dist: demiurge (>=0.2)
Requires-Dist: requests (>=2.7.0)
